{
  "region_gateway_label": "A Fény Fája",
  "region_gateway_pufpufMessage": "A Fény Fája... csodálatos! Gyere velem, hogy felfedezzük! Azt mondják, hogy törzsében ezer alvó világ rejtőzik, amelyek arra várnak, hogy felébredjenek.",
  "region_terra_label": "Terra",
  "region_terra_pufpufMessage": "Ó, a ti bolygótok! Remélem, vendégszerető, ó... haza akarok jutni.",
  "region_lunaria_label": "Lunaria",
  "region_lunaria_pufpufMessage": "Emlékszem, miért indultam el! Lunaria az elveszett bolygó, egyszer a Kelo-Ketis otthonom szomszédbolygója volt!",
  "region_mechanika_label": "Mechanika",
  "region_mechanika_pufpufMessage": "Mindig szerettem a robotokat, de nem a levegőt itt...keresem a vezérlő tornyot, hogy kibővítsem a fa térképét",
  "region_sylvaria_label": "Sylvaria",
  "region_sylvaria_pufpufMessage": "Foszforeszkáló erdők és ösvények, amelyek helyet cserélnek.",
  "region_crystalia_label": "Crystalia",
  "region_crystalia_pufpufMessage": "Fény barlangok és visszhangok, amelyek ötletekkel válaszolnak."
}
